{"title":"Dr.Parted 26.06","link":"https://distrowatch.com/drparted","date":1780309104000,"content":"<img src=\"https://distrowatch.com/images/icon-small/drparted.png\" /> Dr.Parted Live is a bootable GNU/Linux distribution based on Debian's \"Testing\" branch. It is a live image featuring a lightweight Openbox window manager and useful applications for disc partitioning as well as data backup, restore and recovery.","author":"","siteTitle":"DistroWatch","siteHash":"8729f7a89a86da83b12f9be2f8612027c074cb6bd0eb70c929647dea48813434","entryHash":"59bacd6e91387891c9d40a2bb7575ab898afc36673c4ffb1d45ca52840f58fa0","category":"DistroWatch"}